stofory_sdk/__init__.py
stofory_sdk/catalog/.DS_Store
stofory_sdk/catalog/__init__.py
stofory_sdk/catalog/models/.DS_Store
stofory_sdk/catalog/models/__init__.py
stofory_sdk/catalog/models/category.py
stofory_sdk/catalog/models/category_name.py
stofory_sdk/catalog/models/decorator/jsonb_dict.py
stofory_sdk/catalog/models/decorator/ltree_str.py
stofory_sdk/catalog/models/enums/__init__.py
stofory_sdk/catalog/models/enums/content_type.py
stofory_sdk/catalog/models/enums/currency.py
stofory_sdk/catalog/models/enums/locale.py
stofory_sdk/catalog/models/enums/location.py
stofory_sdk/catalog/models/enums/modifier_operator.py
stofory_sdk/catalog/models/enums/parameter_type.py
stofory_sdk/catalog/models/enums/part_of_world.py
stofory_sdk/catalog/models/enums/pricing_type.py
stofory_sdk/catalog/models/enums/product_kind.py
stofory_sdk/catalog/models/enums/product_type.py
stofory_sdk/catalog/models/enums/sync_process_status.py
stofory_sdk/catalog/models/enums/sync_task_priority.py
stofory_sdk/catalog/models/enums/sync_task_status.py
stofory_sdk/catalog/models/enums/sync_task_type.py
stofory_sdk/catalog/models/localization.py
stofory_sdk/catalog/models/origin_platform.py
stofory_sdk/catalog/models/parameter_comment.py
stofory_sdk/catalog/models/parameter_name.py
stofory_sdk/catalog/models/parameter_option.py
stofory_sdk/catalog/models/parameter_option_name.py
stofory_sdk/catalog/models/platform.py
stofory_sdk/catalog/models/product.py
stofory_sdk/catalog/models/product_platform.py
stofory_sdk/catalog/models/product_platform_bonus.py
stofory_sdk/catalog/models/product_platform_category.py
stofory_sdk/catalog/models/product_platform_content.py
stofory_sdk/catalog/models/product_platform_description.py
stofory_sdk/catalog/models/product_platform_discount.py
stofory_sdk/catalog/models/product_platform_external_connection.py
stofory_sdk/catalog/models/product_platform_guarantee.py
stofory_sdk/catalog/models/product_platform_image.py
stofory_sdk-0.3.73.dist-info/METADATA
stofory_sdk-0.3.73.dist-info/WHEEL
stofory_sdk-0.3.73.dist-info/RECORD
