Metadata-Version: 2.1
Name: stofory-sdk
Version: 0.3.73
Summary: 
Author: k
Author-email: nikita.gluhovsky@gmail.com
Requires-Python: >=3.12,<4.0
Classifier: Programming Language :: Python :: 3
Classifier: Programming Language :: Python :: 3.12
Requires-Dist: SQLAlchemy-Utils (>=0,<1)
Requires-Dist: advanced-alchemy (>=0,<1)
Requires-Dist: litestar (>=2,<3)
Requires-Dist: msgspec (>=0.18.6,<0.19.0)
